schema2pyarrow/__init__.py
schema2pyarrow/airbyte_utils.py
schema2pyarrow/exceptions.py
schema2pyarrow/pyarrow_converter.py
schema2pyarrow/schema2pyarrow_cli.py
schema2pyarrow-1.1.6.dist-info/METADATA
schema2pyarrow-1.1.6.dist-info/WHEEL
schema2pyarrow-1.1.6.dist-info/entry_points.txt
schema2pyarrow-1.1.6.dist-info/licenses/LICENSE
schema2pyarrow-1.1.6.dist-info/RECORD
