Metadata-Version: 2.4
Name: schema2pyarrow
Version: 1.1.6
Summary: A schema converter for asyncapi to pyarrow and jsonschema to pyarrow
Project-URL: Homepage, https://github.com/trustedshops-public/schema2pyarrow
Project-URL: Issues, https://github.com/trustedshops-public/schema2pyarrow/issues
Author-email: Data Platform Team Trustedshops <data@trustedshops.com>
License-Expression: MIT
License-File: LICENSE
Keywords: asyncapi,contract,converter,data-contract,jsonschema,schema
Classifier: Operating System :: OS Independent
Classifier: Programming Language :: Python :: 3
Requires-Python: >=3.10
Requires-Dist: pyarrow
Requires-Dist: pyyaml
Requires-Dist: typer
